youtube_series_downloader/__init__.py
youtube_series_downloader/__main__.py
youtube_series_downloader/config.py
youtube_series_downloader/adapters/__init__.py
youtube_series_downloader/adapters/app_adapter.py
youtube_series_downloader/app/__init__.py
youtube_series_downloader/app/download_new_episodes/__init__.py
youtube_series_downloader/app/download_new_episodes/download_new_episodes.py
youtube_series_downloader/app/download_new_episodes/download_new_episodes_repo.py
youtube_series_downloader/app/download_new_episodes/download_new_episodes_test.py
youtube_series_downloader/core/__init__.py
youtube_series_downloader/core/channel.py
youtube_series_downloader/core/video.py
youtube_series_downloader/gateways/__init__.py
youtube_series_downloader/gateways/config_gateway.py
youtube_series_downloader/gateways/config_gateway_test.py
youtube_series_downloader/gateways/ffmpeg_gateway.py
youtube_series_downloader/gateways/sqlite_gateway.py
youtube_series_downloader/gateways/youtube_dl_gateway.py
youtube_series_downloader/gateways/youtube_gateway.py
youtube_series_downloader/gateways/youtube_gateway_test.py
youtube_series_downloader/utils/__init__.py
youtube_series_downloader/utils/arg_parser.py
youtube_series_downloader/utils/log_colors.py
youtube_series_downloader/utils/program_checker.py
youtube_series_downloader-1.6.0.data/data/config/youtube-series-downloader-example.cfg
youtube_series_downloader-1.6.0.dist-info/licenses/LICENSE
youtube_series_downloader-1.6.0.dist-info/METADATA
youtube_series_downloader-1.6.0.dist-info/WHEEL
youtube_series_downloader-1.6.0.dist-info/entry_points.txt
youtube_series_downloader-1.6.0.dist-info/top_level.txt
youtube_series_downloader-1.6.0.dist-info/RECORD
