Metadata-Version: 2.4
Name: youtube-series-downloader
Version: 1.6.0
Summary: Downloads YouTube series and optionally speeds them up to be watched on TVs
Home-page: https://github.com/Senth/youtube-series-downloader
Author: Matteus Magnusson
Author-email: senth.wallace@gmail.com
License: MIT
Classifier: Development Status :: 4 - Beta
Classifier: Environment :: Console
Classifier: License :: OSI Approved :: MIT License
Classifier: Programming Language :: Python :: 3.10
Classifier: Programming Language :: Python :: 3.11
Classifier: Programming Language :: Python :: 3.12
Requires-Python: >=3.10
License-File: LICENSE
Requires-Dist: apscheduler
Requires-Dist: blulib==0.1.1
Requires-Dist: requests
Requires-Dist: tealprint==0.2.1
Requires-Dist: yt-dlp
Dynamic: author
Dynamic: author-email
Dynamic: classifier
Dynamic: description
Dynamic: description-content-type
Dynamic: home-page
Dynamic: license
Dynamic: license-file
Dynamic: requires-dist
Dynamic: requires-python
Dynamic: summary
